taa/__init__.py
taa/cli.py
taa/config.py
taa/dao.py
taa/fixture.py
taa/func.py
taa/logger.py
taa/plugin.py
taa/sample.py
taa/scaffold.py
taa-0.1.1.dist-info/entry_points.txt
taa-0.1.1.dist-info/WHEEL
taa-0.1.1.dist-info/METADATA
taa-0.1.1.dist-info/RECORD
